LaLaaddition_package/__init__.py
LaLaaddition_package/addition.py
LaLaaddition_package-1.9.0.dist-info/METADATA
LaLaaddition_package-1.9.0.dist-info/WHEEL
LaLaaddition_package-1.9.0.dist-info/top_level.txt
LaLaaddition_package-1.9.0.dist-info/RECORD
