Metadata-Version: 2.1
Name: LaLaaddition-package
Version: 1.9.0
Summary: A simple package for performing addition
Author: Nirmit Sakre
